{
  "id": 7,
  "name": "Cities",
  "difficulty": 4,
  "words": {
    "A": ["AACHEN", "AALBORG", "AARHUS", "ABERDEEN", "ABIDJAN", "ABILENE", "ABU DHABI", "ACAPULCO", "ACCRA", "ADDIS ABABA", "ADELAIDE", "ADEN", "AGRA", "AHMEDABAD", "AKRON", "ALBANY", "ALBUQUERQUE", "ALEXANDRIA", "ALGIERS", "ALICANTE", "AMARILLO", "AMMAN", "AMSTERDAM", "ANAHEIM", "ANCHORAGE", "ANDORRA", "ANKARA", "ANN ARBOR", "ANTALYA", "ANTWERP", "APIA", "ARLINGTON", "ASHEVILLE", "ASPEN", "ASTANA", "ATHENS", "ATLANTA", "ATLANTIC CITY", "AUCKLAND", "AUGUSTA", "AURORA", "AUSTIN", "AVIGNON"],
    "B": ["BAGHDAD", "BAKERSFIELD", "BAKU", "BALI", "BALTIMORE", "BAMAKO", "BANGALORE", "BANGKOK", "BANGUI", "BARCELONA", "BARI", "BARRANQUILLA", "BASEL", "BATON ROUGE", "BEIJING", "BEIRUT", "BELFAST", "BELGRADE", "BELIZE CITY", "BERGEN", "BERKELEY", "BERLIN", "BERN", "BETHLEHEM", "BILBAO", "BIRMINGHAM", "BOGOTA", "BOISE", "BOLOGNA", "BOMBAY", "BONN", "BORDEAUX", "BOSTON", "BOULDER", "BRASILIA", "BRATISLAVA", "BREMEN", "BRIDGETOWN", "BRIGHTON", "BRISBANE", "BRISTOL", "BRUGES", "BRUNEI", "BRUSSELS", "BUCHAREST", "BUDAPEST", "BUENOS AIRES", "BUFFALO", "BURLINGTON"],
    "C": ["CAIRO", "CALCUTTA", "CALGARY", "CALI", "CAMBRIDGE", "CANCUN", "CANBERRA", "CAPE TOWN", "CARACAS", "CARDIFF", "CARTAGENA", "CASABLANCA", "CEDAR RAPIDS", "CHARLESTON", "CHARLOTTE", "CHATTANOOGA", "CHENGDU", "CHENNAI", "CHEYENNE", "CHICAGO", "CHIHUAHUA", "CHRISTCHURCH", "CINCINNATI", "CLEVELAND", "COLOGNE", "COLOMBO", "COLORADO SPRINGS", "COLUMBIA", "COLUMBUS", "CONAKRY", "COPENHAGEN", "CORDOBA", "CORK", "CORPUS CHRISTI", "COZUMEL", "CUENCA", "CURITIBA"],
    "D": ["DAKAR", "DALLAS", "DAMASCUS", "DAR ES SALAAM", "DARWIN", "DAYTON", "DELHI", "DENVER", "DES MOINES", "DETROIT", "DHAKA", "DIJON", "DJIBOUTI", "DOHA", "DORTMUND", "DRESDEN", "DUBAI", "DUBLIN", "DULUTH", "DURBAN", "DURHAM", "DUSSELDORF"],
    "E": ["EDINBURGH", "EDMONTON", "EL PASO", "EUGENE", "EVANSVILLE"],
    "F": ["FAIRBANKS", "FARGO", "FAYETTEVILLE", "FLORENCE", "FORTALEZA", "FORT COLLINS", "FORT LAUDERDALE", "FORT WORTH", "FRANKFURT", "FREETOWN", "FREMONT", "FRESNO", "FUKUOKA"],
    "G": ["GABORONE", "GALWAY", "GDANSK", "GENEVA", "GENOA", "GEORGETOWN", "GHENT", "GIBRALTAR", "GLASGOW", "GLENDALE", "GOTHENBURG", "GRANADA", "GRAND RAPIDS", "GRAZ", "GREENSBORO", "GUADALAJARA", "GUANGZHOU", "GUATEMALA CITY", "GUAYAQUIL"],
    "H": ["HAGUE", "HAIFA", "HALIFAX", "HAMBURG", "HAMILTON", "HANGZHOU", "HANOI", "HANOVER", "HARARE", "HARRISBURG", "HARTFORD", "HAVANA", "HEIDELBERG", "HELSINKI", "HENDERSON", "HIROSHIMA", "HO CHI MINH CITY", "HOBART", "HOLLYWOOD", "HONG KONG", "HONOLULU", "HOUSTON", "HUNTSVILLE", "HYDERABAD"],
    "I": ["IBIZA", "INDIANAPOLIS", "INNSBRUCK", "IRVINE", "ISLAMABAD", "ISTANBUL"],
    "J": ["JACKSON", "JACKSONVILLE", "JAIPUR", "JAKARTA", "JERUSALEM", "JOHANNESBURG", "JUNEAU"],
    "K": ["KABUL", "KAMPALA", "KANSAS CITY", "KARACHI", "KATHMANDU", "KHARTOUM", "KIEV", "KIGALI", "KINGSTON", "KINSHASA", "KNOXVILLE", "KOBE", "KOLKATA", "KRAKOW", "KUALA LUMPUR", "KUWAIT CITY", "KYOTO"],
    "L": ["LA PAZ", "LAGOS", "LAHORE", "LANSING", "LAREDO", "LAS VEGAS", "LAUSANNE", "LEEDS", "LEIPZIG", "LEON", "LEXINGTON", "LHASA", "LIBREVILLE", "LILLE", "LIMA", "LIMERICK", "LINCOLN", "LISBON", "LITTLE ROCK", "LIVERPOOL", "LJUBLJANA", "LOME", "LONDON", "LONG BEACH", "LOS ANGELES", "LOUISVILLE", "LUANDA", "LUBLIN", "LUCERNE", "LUSAKA", "LUXEMBOURG", "LYON"],
    "M": ["MACAU", "MADISON", "MADRID", "MALAGA", "MALE", "MANAGUA", "MANAMA", "MANCHESTER", "MANILA", "MAPUTO", "MARRAKECH", "MARSEILLE", "MECCA", "MEDELLIN", "MEDINA", "MELBOURNE", "MEMPHIS", "MERIDA", "MESA", "MESSINA", "MEXICALI", "MEXICO CITY", "MIAMI", "MILAN", "MILWAUKEE", "MINNEAPOLIS", "MINSK", "MOBILE", "MODESTO", "MOGADISHU", "MONACO", "MONROVIA", "MONTERREY", "MONTEVIDEO", "MONTGOMERY", "MONTREAL", "MORELIA", "MOSCOW", "MUMBAI", "MUNICH", "MUSCAT"],
    "N": ["NAGASAKI", "NAGOYA", "NAIROBI", "NANJING", "NANTES", "NAPLES", "NASHVILLE", "NASSAU", "NEW DELHI", "NEW HAVEN", "NEW ORLEANS", "NEW YORK", "NEW YORK CITY", "NEWARK", "NEWCASTLE", "NICE", "NICOSIA", "NORFOLK", "NUREMBERG"],
    "O": ["OAKLAND", "OAXACA", "ODESSA", "OKLAHOMA CITY", "OLYMPIA", "OMAHA", "OPORTO", "ORAN", "ORANGE COUNTY", "ORLANDO", "OSAKA", "OSLO", "OTTAWA", "OUAGADOUGOU", "OXFORD"],
    "P": ["PADUA", "PALERMO", "PALM SPRINGS", "PALMA", "PANAMA CITY", "PARIS", "PASADENA", "PATNA", "PENSACOLA", "PEORIA", "PERTH", "PERUGIA", "PESHAWAR", "PHILADELPHIA", "PHNOM PENH", "PHOENIX", "PISA", "PITTSBURGH", "PLANO", "PLOVDIV", "PORTLAND", "PORTO", "PORTSMOUTH", "POZNAN", "PRAGUE", "PRETORIA", "PRISTINA", "PROVIDENCE", "PUEBLA", "PUERTO VALLARTA", "PUNE", "PYONGYANG"],
    "Q": ["QUEBEC", "QUEBEC CITY", "QUEENSTOWN", "QUERETARO", "QUITO"],
    "R": ["RABAT", "RALEIGH", "RANCHO CUCAMONGA", "RANGOON", "RAPID CITY", "RECIFE", "RENO", "REYKJAVIK", "RICHMOND", "RIGA", "RIO DE JANEIRO", "RIVERSIDE", "RIYADH", "ROCHESTER", "ROME", "ROSARIO", "ROTTERDAM", "ROUEN"],
    "S": ["SACRAMENTO", "SALEM", "SALT LAKE CITY", "SALZBURG", "SAN ANTONIO", "SAN BERNARDINO", "SAN DIEGO", "SAN FRANCISCO", "SAN JOSE", "SAN JUAN", "SAN SALVADOR", "SANAA", "SANTA ANA", "SANTA BARBARA", "SANTA CRUZ", "SANTA FE", "SANTIAGO", "SANTO DOMINGO", "SAO PAULO", "SAPPORO", "SARAJEVO", "SAVANNAH", "SEATTLE", "SENDAI", "SEOUL", "SEVILLE", "SHANGHAI", "SHANNON", "SHENZHEN", "SHREVEPORT", "SIENA", "SINGAPORE", "SIOUX FALLS", "SKOPJE", "SOFIA", "SORRENTO", "SPOKANE", "SPRINGFIELD", "ST LOUIS", "ST PAUL", "ST PETERSBURG", "STAMFORD", "STOCKHOLM", "STRASBOURG", "STUTTGART", "SURABAYA", "SURAT", "SUVA", "SYDNEY", "SYRACUSE"],
    "T": ["TACOMA", "TAIPEI", "TALLAHASSEE", "TALLINN", "TAMPA", "TANGIER", "TASHKENT", "TBILISI", "TEGUCIGALPA", "TEHRAN", "TEL AVIV", "THE HAGUE", "THESSALONIKI", "TIJUANA", "TIRANA", "TOKYO", "TOLEDO", "TORONTO", "TOULOUSE", "TRIPOLI", "TROY", "TUCSON", "TULSA", "TUNIS", "TURIN"],
    "U": ["ULAANBAATAR", "ULM", "ULSAN", "UPPSALA", "UTRECHT", "UTICA"],
    "V": ["VADUZ", "VALENCIA", "VALPARAISO", "VANCOUVER", "VATICAN CITY", "VENICE", "VERACRUZ", "VERONA", "VERSAILLES", "VICTORIA", "VIENNA", "VIENTIANE", "VILNIUS", "VIRGINIA BEACH", "VLADIVOSTOK", "VOLGOGRAD"],
    "W": ["WARSAW", "WASHINGTON", "WASHINGTON DC", "WATERLOO", "WELLINGTON", "WICHITA", "WILMINGTON", "WINDHOEK", "WINNIPEG", "WORCESTER", "WROCLAW", "WUHAN"],
    "X": ["XALAPA", "XIAN", "XIAMEN", "XINING", "XUZHOU"],
    "Y": ["YAKIMA", "YANGON", "YAOUNDE", "YEKATERINBURG", "YELLOWKNIFE", "YEREVAN", "YOKOHAMA", "YONKERS"],
    "Z": ["ZAGREB", "ZANZIBAR", "ZARAGOZA", "ZHENGZHOU", "ZURICH"]
  }
}
