{
  "id": 32,
  "name": "Superheroes",
  "difficulty": 4,
  "words": {
    "A": ["AANG", "ABOMINATION", "ADAM STRANGE", "AGENT COULSON", "AGENT VENOM", "ALFRED", "ALFRED PENNYWORTH", "AMERICA CHAVEZ", "ANCIENT ONE", "ANT MAN", "ANTI VENOM", "APOCALYPSE", "AQUA LAD", "AQUAMAN", "ARCHANGEL", "ARCHIE", "ARES", "ARROW", "ARSENAL", "ATOM", "ATOM SMASHER", "AVATAR", "AVENGERS", "AZRAEL"],
    "B": ["BANE", "BANSHEE", "BARON ZEMO", "BAT MITE", "BATGIRL", "BATMAN", "BATWOMAN", "BEAST", "BEAST BOY", "BEETLE", "BIFROST", "BIG BARDA", "BIRDS OF PREY", "BISHOP", "BLACK ADAM", "BLACK BOLT", "BLACK CAT", "BLACK CANARY", "BLACK KNIGHT", "BLACK LIGHTNING", "BLACK MANTA", "BLACK PANTHER", "BLACK WIDOW", "BLACKFIRE", "BLADE", "BLINK", "BLOB", "BLUE BEETLE", "BLUE MARVEL", "BOLT", "BOOSTER GOLD", "BRAINIAC", "BRUCE BANNER", "BRUCE WAYNE", "BULLSEYE", "BUMBLEBEE"],
    "C": ["CABLE", "CANNONBALL", "CAPTAIN AMERICA", "CAPTAIN ATOM", "CAPTAIN BOOMERANG", "CAPTAIN COLD", "CAPTAIN MARVEL", "CARNAGE", "CASSANDRA CAIN", "CAT GRANT", "CATWOMAN", "CHANGELING", "CLOAK", "CLOAK AND DAGGER", "COLOSSUS", "COMMISSIONER GORDON", "CONAN", "COPPERHEAD", "CORSAIR", "COSMIC BOY", "CRIMSON DYNAMO", "CRYSTAL", "CYBORG", "CYCLOPS"],
    "D": ["DAGGER", "DAMIAN WAYNE", "DAMAGE", "DAREDEVIL", "DARK PHOENIX", "DARKSEID", "DARKSTAR", "DAZZLER", "DC COMICS", "DEADMAN", "DEADPOOL", "DEADSHOT", "DEATH", "DEATHSTROKE", "DESTROYER", "DETECTIVE", "DEVIL DINOSAUR", "DICK GRAYSON", "DOC OCTOPUS", "DOC SAMSON", "DOCTOR DOOM", "DOCTOR FATE", "DOCTOR MANHATTAN", "DOCTOR OCTOPUS", "DOCTOR STRANGE", "DOMINO", "DONNA TROY", "DOOM", "DORMAMMU", "DRAX", "DRAX THE DESTROYER", "DREAM"],
    "E": ["ECHO", "EGO", "ELASTIGIRL", "ELECTRO", "ELEKTRA", "ELEMENT LAD", "ELONGATED MAN", "EMMA FROST", "ENCHANTRESS", "ENIGMA", "ETERNALS", "ETRIGAN", "EXCALIBUR"],
    "F": ["FALCON", "FALCON AND WINTER SOLDIER", "FANTASTIC FOUR", "FATE", "FIRESTAR", "FIRESTORM", "FISK", "FLASH", "FLASH GORDON", "FORGE", "FRANKLIN RICHARDS", "FROZONE", "FURY"],
    "G": ["GALACTUS", "GAMBIT", "GAMORA", "GHOST", "GHOST RIDER", "GIANT MAN", "GLADIATOR", "GODZILLA", "GORILLA GRODD", "GOTHAM", "GREEN ARROW", "GREEN GOBLIN", "GREEN LANTERN", "GROOT", "GUARDIANS", "GUARDIANS OF GALAXY", "GUY GARDNER"],
    "H": ["HAL JORDAN", "HANK PYM", "HARLEY QUINN", "HAVOK", "HAWK", "HAWKEYE", "HAWKGIRL", "HAWKMAN", "HELA", "HELLBOY", "HELLFIRE CLUB", "HERCULES", "HIT GIRL", "HOBGOBLIN", "HOPE", "HOPE SUMMERS", "HOURMAN", "HOWARD THE DUCK", "HULK", "HULKBUSTER", "HUMAN TORCH", "HUNTRESS", "HYPERION", "HYDRA"],
    "I": ["ICEMAN", "IKARIS", "IMMORTAL", "IMPOSSIBLE MAN", "IMPULSE", "INCREDIBLE HULK", "INCREDIBLES", "INFAMOUS IRON MAN", "INHUMANS", "INVINCIBLE", "INVISIBLE WOMAN", "IRON FIST", "IRON MAN", "IRON MONGER"],
    "J": ["J JONAH JAMESON", "JACK KNIGHT", "JARVIS", "JASON TODD", "JEAN GREY", "JESSICA DREW", "JESSICA JONES", "JIM GORDON", "JIMMY OLSEN", "JINX", "JOHN CONSTANTINE", "JOHN STEWART", "JOHN WICK", "JOKER", "JONAH HEX", "JUBILEE", "JUGGERNAUT", "JUSTICE LEAGUE", "JUSTICE SOCIETY"],
    "K": ["KA ZAR", "KAINE", "KAMALA KHAN", "KANG", "KANG THE CONQUEROR", "KATE BISHOP", "KATE KANE", "KATMA TUI", "KICK ASS", "KID FLASH", "KILLER CROC", "KILLER FROST", "KILOWOG", "KING SHARK", "KINGPIN", "KITTY PRYDE", "KNIGHT", "KNOWHERE", "KORG", "KRAKOA", "KRAVEN", "KREE", "KRYPTON", "KRYPTONITE"],
    "L": ["LADY DEADPOOL", "LADY DEATHSTRIKE", "LANE", "LARA CROFT", "LEGION", "LEGION OF DOOM", "LEGOLAS", "LEVIATHAN", "LEX LUTHOR", "LIGHTNING LAD", "LIVING TRIBUNAL", "LIZARD", "LOIS LANE", "LOKI", "LONGSHOT", "LOBO", "LUCY LANE", "LUKE CAGE", "LUKE SKYWALKER"],
    "M": ["MAD HATTER", "MADAM WEB", "MADAME HYDRA", "MAGENTO", "MAGIK", "MAGNETO", "MAN BAT", "MAN THING", "MANDARIN", "MANTIS", "MANTA", "MARVEX", "MARVEL", "MARVEL COMICS", "MARVEL GIRL", "MARY JANE", "MASTER CHIEF", "MEDUSA", "MEPHISTO", "METALLO", "METAMORPHO", "MIDNIGHT", "MILES MORALES", "MIRACLE MAN", "MISS AMERICA", "MISS MARTIAN", "MISTER FANTASTIC", "MISTER FREEZE", "MISTER MIRACLE", "MISTER SINISTER", "MISTER TERRIFIC", "MOCKINGBIRD", "MODOK", "MOJO", "MOLECULE MAN", "MOLTEN MAN", "MONGUL", "MONITOR", "MOON KNIGHT", "MOONDRAGON", "MOONSTAR", "MORBIUS", "MORPH", "MOTION", "MS MARVEL", "MULTIPLE MAN", "MYSTIQUE"],
    "N": ["NAMOR", "NAMORA", "NAMORITA", "NEBULA", "NEGATIVE MAN", "NEMESIS", "NICK FURY", "NIGHT GIRL", "NIGHT THRASHER", "NIGHTCRAWLER", "NIGHTHAWK", "NIGHTWING", "NIMROD", "NITE OWL", "NORTHSTAR", "NOVA"],
    "O": ["OBERON", "ODIN", "OKOYE", "OMEGA MEN", "OMEGA RED", "OMNI MAN", "ONOMATOPOEIA", "ORACLE", "ORCA", "ORION", "OSIRIS", "OUTSIDERS", "OWL"],
    "P": ["PALADIN", "PANDORA", "PARASITE", "PATRIOT", "PENGUIN", "PENANCE", "PEPPER POTTS", "PETER PARKER", "PETER QUILL", "PHANTOM", "PHANTOM STRANGER", "PHOENIX", "PIP", "PLASTIC MAN", "POISON IVY", "POLARIS", "PORCUPINE", "POWER GIRL", "POWER MAN", "PRINCESS LEIA", "PROFESSOR X", "PROFESSOR ZOOM", "PROMETHEUS", "PROWLER", "PSYLOCKE", "PUNISHER", "PURPLE MAN"],
    "Q": ["QUASAR", "QUEEN HIPPOLYTA", "QUESTION", "QUICKSILVER", "QUILL"],
    "R": ["RA'S AL GHUL", "RADIOACTIVE MAN", "RAGMAN", "RAGNAROK", "RAIN", "RAPTOR", "RAVEN", "RAY", "RAZER", "RED ARROW", "RED GUARDIAN", "RED HOOD", "RED HULK", "RED ROBIN", "RED SKULL", "RED TORNADO", "REVERSE FLASH", "RHINO", "RIDDLER", "RICTOR", "RIRI WILLIAMS", "ROBIN", "ROBOCOP", "ROCKETEER", "ROCKET RACCOON", "ROGUE", "RORSCHACH", "RUNAWAYS"],
    "S": ["SABRETOOTH", "SANDMAN", "SAPPHIRE", "SASQUATCH", "SAVAGE DRAGON", "SCARECROW", "SCARLET", "SCARLET SPIDER", "SCARLET WITCH", "SCORPION", "SENTRY", "SERSI", "SHADOW KING", "SHADOWCAT", "SHANG CHI", "SHANNA", "SHATTERSTAR", "SHAZAM", "SHE HULK", "SHIELD", "SHOCKER", "SHRIEK", "SHURI", "SIDESHOW BOB", "SILK", "SILVER SAMURAI", "SILVER SURFER", "SILVERMANE", "SINESTRO", "SIRYN", "SKAAR", "SKRULL", "SLADE", "SLAPSTICK", "SLEEPWALKER", "SOLO", "SONGBIRD", "SPAWN", "SPECTRE", "SPEED", "SPEEDY", "SPIDER BOY", "SPIDER GIRL", "SPIDER GWEN", "SPIDER HAM", "SPIDER MAN", "SPIDER WOMAN", "SPOT", "SQUIRREL GIRL", "STAR", "STAR BRAND", "STAR LORD", "STAR SAPPHIRE", "STARFIRE", "STARGIRL", "STARMAN", "STATIC", "STATIC SHOCK", "STEEL", "STEPHANIE BROWN", "STEVE ROGERS", "STONE", "STORM", "STRANGE", "STRIPE", "STRONG GUY", "STRYFE", "SUB MARINER", "SUNFIRE", "SUNSPOT", "SUPERBOY", "SUPERGIRL", "SUPERMAN", "SWAMP THING", "SWITCH", "SWORDSMAN"],
    "T": ["T'CHALLA", "TALBOT", "TALON", "TALOS", "TARA", "TASKMASTER", "TEEN TITANS", "TEMPEST", "TERRA", "TERRAX", "THANOS", "THEA QUEEN", "THE ATOM", "THE BATMAN", "THE BEAST", "THE BLOB", "THE FLASH", "THE HOOD", "THE HULK", "THE THING", "THE VULTURE", "THING", "THOR", "THROG", "THUNDER", "THUNDERBOLTS", "THUNDERSTRIKE", "TIGRA", "TIM DRAKE", "TITAN", "TITANIA", "TITANS", "TOAD", "TOMBSTONE", "TONY STARK", "TRICKSTER", "TRIDENT", "TRITON", "TROPHY", "TURN", "TWO FACE"],
    "U": ["UATU", "ULTRA BOY", "ULTRAFORCE", "ULTRAMAN", "ULTRAVIOLET", "ULTIMATE SPIDER MAN", "ULTRON", "UNCLE BEN", "UNDERDOG", "UNKNOWN SOLDIER"],
    "V": ["VALKYRIE", "VALOR", "VANDAL SAVAGE", "VENOM", "VERTIGO", "VIBE", "VIGILANTE", "VILLAIN", "VINDICATOR", "VIOLATOR", "VIPER", "VISION", "VIXEN", "VOLCANA", "VULCAN", "VULTURE"],
    "W": ["WAKANDA", "WALLY WEST", "WAR MACHINE", "WARBIRD", "WARLOCK", "WARLORD", "WASP", "WATCHER", "WATCHMEN", "WAVE", "WEAPON X", "WHIPLASH", "WHITE CANARY", "WHITE QUEEN", "WHITE TIGER", "WHITE WITCH", "WICCAN", "WILDCAT", "WINTER SOLDIER", "WITCHBLADE", "WIZARD", "WOK", "WOLFSBANE", "WOLVERINE", "WONDER GIRL", "WONDER MAN", "WONDER WOMAN", "WONG", "WORLD WAR HULK"],
    "X": ["X 23", "X FACTOR", "X FORCE", "X MAN", "X MEN", "XAVIER", "XENA", "XORN"],
    "Y": ["YELLOWJACKET", "YONDU", "YOUNG AVENGERS", "YOUNG JUSTICE"],
    "Z": ["ZATANNA", "ZATARA", "ZEBRA MAN", "ZOD", "ZOOM", "ZORRO"]
  }
}
